cfgcaddy/__init__.py
cfgcaddy/__main__.py
cfgcaddy/config.py
cfgcaddy/file_state.py
cfgcaddy/link.py
cfgcaddy/link_spec.py
cfgcaddy/linker.py
cfgcaddy/publish.py
cfgcaddy/utils.py
cfgcaddy-0.1.8.dist-info/entry_points.txt
cfgcaddy-0.1.8.dist-info/WHEEL
cfgcaddy-0.1.8.dist-info/METADATA
cfgcaddy-0.1.8.dist-info/RECORD
