Metadata-Version: 2.1
Name: cfgcaddy
Version: 0.1.8
Summary: A cli for managing user's config files
License: MIT
Author: Tyler Stapler
Author-email: tystapler@gmail.com
Requires-Python: >=3.7,<4.0.0
Classifier: License :: OSI Approved :: MIT License
Classifier: Programming Language :: Python :: 3
Classifier: Programming Language :: Python :: 3.10
Classifier: Programming Language :: Python :: 3.7
Classifier: Programming Language :: Python :: 3.8
Classifier: Programming Language :: Python :: 3.9
Requires-Dist: click (>=8.0.0,<9.0.0)
Requires-Dist: pathspec (>=0.8.1)
Requires-Dist: questionary (>=1.9.0,<2.0.0)
Requires-Dist: ruamel.yaml (>=0.16.12,<0.17.0)
